Metadata-Version: 1.2
Name: btrfs-quota
Version: 0.1.0
Summary: BtrFS quota management helper
Home-page: UNKNOWN
Author: Dmitrry Orlov
Author-email: me@mosquito.su
License: UNKNOWN
Keywords: btrfs,tools,tool,quota,qgroup
Platform: POSIX
Classifier: License :: OSI Approved :: Apache Software License
Classifier: Topic :: Internet
Classifier: Topic :: Software Development
Classifier: Topic :: Software Development :: Libraries
Classifier: Intended Audience :: Developers
Classifier: Natural Language :: English
Classifier: Operating System :: MacOS
Classifier: Operating System :: POSIX
Classifier: Programming Language :: Python
Classifier: Programming Language :: Python :: 3
Classifier: Programming Language :: Python :: 3.5
Classifier: Programming Language :: Python :: 3.6
Classifier: Programming Language :: Python :: 3.7
Classifier: Programming Language :: Python :: 3.8
Classifier: Programming Language :: Python :: 3.9
Classifier: Programming Language :: Python :: Implementation :: CPython
Requires-Python: >3.5.*
